{
    "name": "Checklist",
    "base": "PersistedModel",
    "idInjection": true,
    "options": {
        "validateUpsert": true
    },
    "properties": {
        "title": {
            "type": "string"
        },
        "budget": {
            "type": "number"
        },
        "isDone": {
            "type": "boolean"
        },
        "userIds": {
            "type": [
                "string"
            ]
        }
    },
    "validations": [],
    "relations": {
        "taskId": {
            "type": "belongsTo",
            "model": "Task",
            "foreignKey": "taskId"
        }
    },
    "acls": [],
    "methods": {}
}